{"PLANETAS":[{"porcentajeMuertes":0.052251816,"naves":5,"nombre":"Ewn","produccion":10},{"porcentajeMuertes":0.19531345,"naves":5,"nombre":"ñD","produccion":10},{"porcentajeMuertes":0.6682747,"naves":5,"nombre":"dab","produccion":10}],"JUGADORES":[{"planetas":["Ewn"],"tipo":"HUMANO","nombre":"Jugador1"},{"planetas":["ñD"],"tipo":"HUMANO","nombre":"Jugador2"},{"planetas":["dab"],"tipo":"HUMANO","nombre":"Jugador3"}],"PLANETAS_NEUTRALES":[{"porcentajeMuertes":0.4889353,"naves":5,"nombre":"mvf","produccion":5},{"porcentajeMuertes":0.37523717,"naves":5,"nombre":"qj","produccion":5},{"porcentajeMuertes":0.18264931,"naves":5,"nombre":"UsD","produccion":5},{"porcentajeMuertes":0.15167451,"naves":5,"nombre":"YU","produccion":5},{"porcentajeMuertes":0.6954777,"naves":5,"nombre":"oXQ","produccion":5},{"porcentajeMuertes":0.8572856,"naves":5,"nombre":"nbo","produccion":5},{"porcentajeMuertes":0.78143525,"naves":5,"nombre":"ifFA","produccion":5},{"porcentajeMuertes":0.8651019,"naves":5,"nombre":"fzs","produccion":5}],"MAPA":{"NEUTRALES":{"mostrarNaves":false,"mostrarEstadisticas":false,"produccion":10},"alAzar":false,"tamaño":{"filas":8,"columnas":5},"mapaCiego":true,"acumular":true,"id":"kjhkj","planetasNeutrales":8,"finalizacion":50}}